kbraincortex/ai/reasoning.py
kbraincortex/api/__init__.py
kbraincortex/api/accounts.py
kbraincortex/api/keys.py
kbraincortex/api/telemetry.py
kbraincortex/azure/__init__.py
kbraincortex/azure/cosmos.py
kbraincortex/azure/datafactory.py
kbraincortex/azure/openai.py
kbraincortex/azure/search.py
kbraincortex/azure/service_bus.py
kbraincortex/common/__init__.py
kbraincortex/common/configuration.py
kbraincortex/events/websockets.py
kbraincortex/exceptions/collection.py
kbraincortex/guidance/azure.py
kbraincortex/ingest/onedrive.py
kbraincortex/ingest/rfp_responses.py
kbraincortex/ingest/sharepoint.py
kbraincortex/ingest/status.py
kbraincortex/llms/encodings.py
kbraincortex/llms/generation.py
kbraincortex/llms/meta.py
kbraincortex/llms/mistral.py
kbraincortex/llms/models.py
kbraincortex/microsoft/graph.py
kbraincortex/microsoft/msal.py
kbraincortex/rag/__init__.py
kbraincortex/rag/datasets.py
kbraincortex/rag/retrieval.py
kbraincortex/taxonomy/categories.py
kbraincortex/taxonomy/tagging.py
kbraincortex-0.14.15.dist-info/METADATA
kbraincortex-0.14.15.dist-info/WHEEL
kbraincortex-0.14.15.dist-info/RECORD
