Metadata-Version: 2.1
Name: kbraincortex
Version: 0.14.15
Summary: Common KBRaiN Functions
License: unlicensed
Author: Daniel Eric Fredriksen
Author-email: daniel.fredriksen@us.kbr.com
Requires-Python: >=3.11,<4.0
Classifier: License :: Other/Proprietary License
Classifier: Programming Language :: Python :: 3
Classifier: Programming Language :: Python :: 3.11
Classifier: Programming Language :: Python :: 3.12
Requires-Dist: applicationinsights (>=0.11.10,<0.12.0)
Requires-Dist: azure-core (>=1.29.5,<2.0.0)
Requires-Dist: azure-cosmos (>=4.5.1,<5.0.0)
Requires-Dist: azure-identity (>=1.15.0,<2.0.0)
Requires-Dist: azure-mgmt-datafactory (>=4.0.0,<5.0.0)
Requires-Dist: azure-search (>=1.0.0b2,<2.0.0)
Requires-Dist: azure-search-documents (==11.4.0b6)
Requires-Dist: azure-servicebus (>=7.12.2,<8.0.0)
Requires-Dist: bcrypt (>=4.0.1,<5.0.0)
Requires-Dist: datetime (>=5.3,<6.0)
Requires-Dist: guidance (>=0.1.10,<0.2.0)
Requires-Dist: kbrainsdk (==0.14.8)
Requires-Dist: nest-asyncio (>=1.5.8,<2.0.0)
Requires-Dist: numpy (>=1.26.2,<2.0.0)
Requires-Dist: openai (>=1.3.3,<2.0.0)
Requires-Dist: python-dotenv (>=1.0.0,<2.0.0)
Requires-Dist: requests (>=2.31.0,<3.0.0)
Requires-Dist: websockets (>=12.0,<13.0)
